mdtf_test_data/__init__.py
mdtf_test_data/config/cmip_3hr.yml
mdtf_test_data/config/cmip_day.yml
mdtf_test_data/config/cmip_mon.yml
mdtf_test_data/config/gfdl_day.yml
mdtf_test_data/config/ncar_1hr.yml
mdtf_test_data/config/ncar_3hr.yml
mdtf_test_data/config/ncar_day.yml
mdtf_test_data/config/ncar_mon.yml
mdtf_test_data/generators/__init__.py
mdtf_test_data/generators/convective.py
mdtf_test_data/generators/normal.py
mdtf_test_data/resources/ocean_static_5deg.nc
mdtf_test_data/synthetic/__init__.py
mdtf_test_data/synthetic/synthetic_data.py
mdtf_test_data/synthetic/synthetic_setup.py
mdtf_test_data/synthetic/horizontal/__init__.py
mdtf_test_data/synthetic/horizontal/construct_rect_grid.py
mdtf_test_data/synthetic/horizontal/construct_tripolar_grid.py
mdtf_test_data/synthetic/time/__init__.py
mdtf_test_data/synthetic/time/time.py
mdtf_test_data/synthetic/vertical/__init__.py
mdtf_test_data/synthetic/vertical/cmip_vertical_coord.py
mdtf_test_data/synthetic/vertical/gfdl_plev19_vertical_coord.py
mdtf_test_data/synthetic/vertical/gfdl_vertical_coord.py
mdtf_test_data/synthetic/vertical/mom6_rho2_coord.py
mdtf_test_data/synthetic/vertical/mom6_z_coord.py
mdtf_test_data/synthetic/vertical/ncar_hybrid_coord.py
mdtf_test_data/tests/__init__.py
mdtf_test_data/tests/ref_synth_dset.nc
mdtf_test_data/tests/test_construct_rect_grid.py
mdtf_test_data/tests/test_construct_tripolar_grid.py
mdtf_test_data/tests/test_generators.py
mdtf_test_data/tests/test_synthetic_data.py
mdtf_test_data/util/__init__.py
mdtf_test_data/util/cli.py
mdtf_test_data/util/mdtf-coarsen.py
mdtf_test_data/util/mdtf_src_query.py
mdtf_test_data/util/rectilinear.py
mdtf_test_data-1.0.9.data/scripts/mdtf_synthetic.py
scripts/__init__.py
scripts/mdtf_synthetic.py
mdtf_test_data-1.0.9.dist-info/LICENSE.txt
mdtf_test_data-1.0.9.dist-info/METADATA
mdtf_test_data-1.0.9.dist-info/WHEEL
mdtf_test_data-1.0.9.dist-info/top_level.txt
mdtf_test_data-1.0.9.dist-info/RECORD
