Metadata-Version: 2.2
Name: mdtf_test_data
Version: 1.0.9
Summary: Tools for working with MDTF Diagnostics test data sets
Home-page: https://github.com/jkrasting/mdtf_test_data
Author: MDTF Development Team
Author-email: oar.gfdl.mdtf@noaa.gov
Keywords: process-oriented diagnostics climate weather mdtf
Classifier: Development Status :: 5 - Production/Stable
Classifier: Intended Audience :: Science/Research
Classifier: Topic :: Scientific/Engineering
Classifier: License :: Public Domain
Classifier: Programming Language :: Python :: 3.7
Classifier: Programming Language :: Python :: 3.8
Classifier: Programming Language :: Python :: 3.9
Requires-Python: >=3.7
License-File: LICENSE.txt
Requires-Dist: cftime
Requires-Dist: envyaml
Requires-Dist: netcdf4
Requires-Dist: numpy>=1.17
Requires-Dist: xarray>=0.17.0
